MANIFEST.in
README.txt
setup.cfg
setup.py
./MANIFEST.in
./README.txt
./setup.cfg
./setup.py
./collective/__init__.py
./collective/multilogo/README.txt
./collective/multilogo/__init__.py
./collective/multilogo/configure.zcml
./collective/multilogo/i18ndude.sh
./collective/multilogo/interfaces.py
./collective/multilogo/setuphandlers.py
./collective/multilogo/tests.py
./collective/multilogo/browser/__init__.py
./collective/multilogo/browser/configure.zcml
./collective/multilogo/browser/controlpanel.py
./collective/multilogo/browser/multilogo.css
./collective/multilogo/browser/multilogo.pt
./collective/multilogo/browser/viewlets.py
./collective/multilogo/locales/collective.multilogo.pot
./collective/multilogo/locales/manual.pot
./collective/multilogo/locales/cs/LC_MESSAGES/collective.multilogo.mo
./collective/multilogo/locales/cs/LC_MESSAGES/collective.multilogo.po
./collective/multilogo/profiles/default/actionicons.xml
./collective/multilogo/profiles/default/browserlayer.xml
./collective/multilogo/profiles/default/controlpanel.xml
./collective/multilogo/profiles/default/cssregistry.xml
./collective/multilogo/profiles/default/import_steps.xml
./collective/multilogo/profiles/default/metadata.xml
./collective/multilogo/profiles/default/multilogo.txt
./collective/multilogo/profiles/default/viewlets.xml
./collective/multilogo/profiles/uninstall/import_steps.xml
./collective/multilogo/profiles/uninstall/multilogo-uninstall.txt
./collective/multilogo/profiles/uninstall/viewlets.xml
./docs/HISTORY.txt
./docs/INSTALL.txt
./docs/LICENSE.GPL
./docs/LICENSE.txt
collective/__init__.py
collective.multilogo.egg-info/PKG-INFO
collective.multilogo.egg-info/SOURCES.txt
collective.multilogo.egg-info/dependency_links.txt
collective.multilogo.egg-info/entry_points.txt
collective.multilogo.egg-info/namespace_packages.txt
collective.multilogo.egg-info/not-zip-safe
collective.multilogo.egg-info/requires.txt
collective.multilogo.egg-info/top_level.txt
collective/multilogo/README.txt
collective/multilogo/__init__.py
collective/multilogo/configure.zcml
collective/multilogo/i18ndude.sh
collective/multilogo/interfaces.py
collective/multilogo/setuphandlers.py
collective/multilogo/tests.py
collective/multilogo/browser/__init__.py
collective/multilogo/browser/configure.zcml
collective/multilogo/browser/controlpanel.py
