Metadata-Version: 1.0
Name: collective.multilogo
Version: 0.2
Summary: A Plone extension package providing wiewlet with user defined multiple portal logos.
Home-page: http://svn.plone.org/svn/collective/collective.multilogo
Author: Lukas Zdych
Author-email: lukas.zdych@gmail.com
License: GPL
Keywords: plone,logo
Platform: UNKNOWN
Classifier: Framework :: Plone
Classifier: Programming Language :: Python
Classifier: Topic :: Software Development :: Libraries :: Python Modules
